omnimail/__init__.py
omnimail-0.1.0.dist-info/licenses/LICENSE
omnimail-0.1.0.dist-info/METADATA
omnimail-0.1.0.dist-info/WHEEL
omnimail-0.1.0.dist-info/top_level.txt
omnimail-0.1.0.dist-info/RECORD
