Metadata-Version: 2.4
Name: omnimail
Version: 0.1.0
Summary: A unified email library supporting SMTP, OAuth2, and API-based sending
Author-email: Stephen Glombicki <github@sglombicki.com>
License: MIT
Classifier: Programming Language :: Python :: 3
Classifier: License :: OSI Approved :: MIT License
Classifier: Topic :: Communications :: Email
Requires-Python: >=3.7
License-File: LICENSE
Dynamic: license-file
